gitme/__init__.py
gitme/command_controller.py
gitme/entrypoint.py
gitme/git_controller.py
gitme/gitlab_controller.py
gitme/log.py
tests/__init__.py
tests/git_command.py
tests/test_git_controller.py
tests/test_gitlab_api.py
tests/test_gitlab_controller.py
tests/test_run_command.py
gitme-0.3.1.dist-info/METADATA
gitme-0.3.1.dist-info/WHEEL
gitme-0.3.1.dist-info/entry_points.txt
gitme-0.3.1.dist-info/top_level.txt
gitme-0.3.1.dist-info/RECORD
