Metadata-Version: 2.1
Name: gitme
Version: 0.3.1
Summary: create merge requests on gitlab, based on changes already done
Home-page: http://github.com/aufbaubank/gitme
Author: Daniel Henneberg
Author-email: daniel.henneberg@aufbaubank.de
License: MIT
Platform: UNKNOWN
Classifier: Development Status :: 3 - Alpha
Classifier: Environment :: Console
Classifier: Intended Audience :: Developers
Classifier: Intended Audience :: System Administrators
Classifier: Topic :: Utilities
Classifier: License :: OSI Approved :: MIT License
Classifier: Programming Language :: Python :: 3.6
Classifier: Programming Language :: Python :: 3.8
Requires-Python: >=3.6
Requires-Dist: requests
Requires-Dist: GitPython
